LICENSE
light_aligner/__init__.py
light_aligner/__main__.py
light_aligner/align_sents.py
light_aligner/bingmdx_tr.py
light_aligner/browse_filename.py
light_aligner/check_anchors.py
light_aligner/color_table_applymap.py
light_aligner/common_prefix.py
light_aligner/coverage_rate.py
light_aligner/find_aligned_pairs.py
light_aligner/gen_filename.py
light_aligner/gen_row_alignment.py
light_aligner/gen_wlength_vec.py
light_aligner/get_filename.py
light_aligner/light_aligner.py
light_aligner/light_scores.py
light_aligner/load_paras.py
light_aligner/load_xlsx.py
light_aligner/msbing_c_e.msgpk
light_aligner/msbing_c_e_ehw.msgpk
light_aligner/msbing_c_e_hw.msgpk
light_aligner/plist_to_slist.py
light_aligner/read_text.py
light_aligner/save_xlsx.py
light_aligner/single_or_dual.py
light_aligner/stopwords/.git/config
light_aligner/stopwords/.git/description
light_aligner/stopwords/.git/HEAD
light_aligner/stopwords/.git/hooks/applypatch-msg.sample
light_aligner/stopwords/.git/hooks/commit-msg.sample
light_aligner/stopwords/.git/hooks/fsmonitor-watchman.sample
light_aligner/stopwords/.git/hooks/post-update.sample
light_aligner/stopwords/.git/hooks/pre-applypatch.sample
light_aligner/stopwords/.git/hooks/pre-commit.sample
light_aligner/stopwords/.git/hooks/pre-merge-commit.sample
light_aligner/stopwords/.git/hooks/pre-push.sample
light_aligner/stopwords/.git/hooks/pre-rebase.sample
light_aligner/stopwords/.git/hooks/pre-receive.sample
light_aligner/stopwords/.git/hooks/prepare-commit-msg.sample
light_aligner/stopwords/.git/hooks/update.sample
light_aligner/stopwords/.git/index
light_aligner/stopwords/.git/info/exclude
light_aligner/stopwords/.git/logs/HEAD
light_aligner/stopwords/.git/logs/refs/heads/master
light_aligner/stopwords/.git/logs/refs/remotes/origin/HEAD
light_aligner/stopwords/.git/objects/09/002cceefe2e47487b21d5d6cf49c60ef3c1ee5
light_aligner/stopwords/.git/objects/14/eb732aacbc1b3196b092da09a2c1a126d7b8c1
light_aligner-0.1.4.dist-info/entry_points.txt
light_aligner-0.1.4.dist-info/LICENSE
light_aligner-0.1.4.dist-info/WHEEL
light_aligner-0.1.4.dist-info/METADATA
light_aligner-0.1.4.dist-info/RECORD
