Metadata-Version: 2.1
Name: light-aligner
Version: 0.1.4
Summary: a light-weight aligner.
Home-page: https://github.com/ffreemt/light-aligner
Author: ffreemt
Requires-Python: >=3.6.1,<4.0.0
Classifier: Programming Language :: Python :: 3
Classifier: Programming Language :: Python :: 3.7
Classifier: Programming Language :: Python :: 3.8
Classifier: Programming Language :: Python :: 3.9
Requires-Dist: PyStarDict (>=0.8,<0.9)
Requires-Dist: absl-py (>=0.12.0,<0.13.0)
Requires-Dist: blinker (>=1.4,<2.0)
Requires-Dist: cchardet (>=2.1.6,<3.0.0)
Requires-Dist: chardet (>=3.0.4,<4.0.0)
Requires-Dist: diskcache (>=5.2.1,<6.0.0)
Requires-Dist: flake8 (>=3.8.3,<4.0.0)
Requires-Dist: langid (>=1.1.6,<2.0.0)
Requires-Dist: linetimer (>=0.1.4,<0.2.0)
Requires-Dist: logzero (>=1.5.0,<2.0.0)
Requires-Dist: matplotlib (>=3.3.0,<4.0.0)
Requires-Dist: msgpack (>=1.0.0,<2.0.0)
Requires-Dist: openpyxl (>=3.0.4,<4.0.0)
Requires-Dist: orjson (>=3.3.0,<4.0.0)
Requires-Dist: pandas (>=1.1.0,<2.0.0)
Requires-Dist: polyglot (>=16.7.4,<17.0.0)
Requires-Dist: pyquery (>=1.4.1,<2.0.0)
Requires-Dist: pyspellchecker (>=0.5.5,<0.6.0)
Requires-Dist: rank_bm25 (>=0.2.1,<0.3.0)
Requires-Dist: seaborn (>=0.11.1,<0.12.0)
Requires-Dist: sentence-splitter (>=1.4,<2.0)
Requires-Dist: textblob (>=0.15.3,<0.16.0)
Requires-Dist: textblob-de (>=0.4.3,<0.5.0)
Requires-Dist: ujson (>=3.1.0,<4.0.0)
Requires-Dist: xlrd (>=1.2.0,<2.0.0)
Requires-Dist: yaspin (>=1.0.0,<2.0.0)
Project-URL: Repository, https://github.com/ffreemt/light-aligner
